{"dependencies":[{"name":"./style.css","dynamic":true},{"name":"./img/GitHub_Logo.png","dynamic":true},{"name":"./dist/app.js","dynamic":true}],"generated":{"html":"<!DOCTYPE html>\n<html xmlns=\"http://www.w3.org/1999/xhtml\" lang=\"en\">\n<head>\n  <meta charset=\"utf-8\">\n  <title>Bitcoin Watchlist</title>\n  <meta name=\"viewport\" content=\"width=device-width, initial-scale=1\">\n  <meta property=\"fb:app_id\" content=\"1968068840134141\">\n  <meta property=\"og:url\" content=\"https://mycaule.github.io/portfolo\">\n  <meta property=\"og:type\" content=\"website\">\n  <meta property=\"og:title\" content=\"Bitcoin Watchlist\">\n  <meta property=\"og:description\" content=\"Bitcoin Watchlist\">\n  <meta property=\"og:image\" content=\"https://dummyimage.com/600x400/000/fff\">\n  <link rel=\"stylesheet\" href=\"https://dev.mavo.io/dist/mavo.css\">\n  <link rel=\"stylesheet\" href=\"/dist/0f361953c313b9429969d0b5b4edc960.css\">\n</head>\n\n<body mv-app=\"\" mv-storage=\"local\" mv-autosave=\"0\" mv-bar=\"none\">\n  <div id=\"fb-root\"></div>\n  <script>\n    (function(d, s, id) {\n      var js, fjs = d.getElementsByTagName(s)[0];\n      if (d.getElementById(id)) return;\n      js = d.createElement(s); js.id = id;\n      js.src = 'https://connect.facebook.net/en_US/sdk.js#xfbml=1&version=v2.11&appId=1968068840134141';\n      fjs.parentNode.insertBefore(js, fjs);\n    }(document, 'script', 'facebook-jssdk'));\n  </script>\n\n  <header>\n    <h2>Bitcoin Watchlist</h2>\n  </header>\n\n  <main>\n    <input type=\"hidden\" value=\"[onchange(base, currency)]\" property=\"_change\">\n    <input type=\"hidden\" property=\"spot\">\n    <input type=\"hidden\" property=\"checked_time\">\n    <input type=\"hidden\" property=\"checked_date\">\n\n    Data as of:<br>\n    [checked_time]<br>\n    on [checked_date]<br>\n\n    <h3>Summary</h3>\n    1.00 <select property=\"base\"></select> = [spot] <select property=\"currency\"></select>\n  </main>\n<hr>    <div id=\"myChart\"></div>\n  <footer>\n    <div class=\"fb-comments\" data-href=\"https://mycaule.github.io/portfolio\" data-numposts=\"5\"></div>\n\n    <div>\n      <div class=\"fb-like\" data-href=\"https://mycaule.github.io/portfolio\" data-layout=\"button_count\" data-action=\"recommend\" data-size=\"large\" data-show-faces=\"true\" data-share=\"true\"></div>\n    </div>\n    <div>\n      <a href=\"https://github.com/mycaule/portfolio\"><img src=\"/dist/639208ad73968de3021f58ffaf2efbb9.png\" height=\"20\" alt=\"GitHub\"></a>\n    </div>\n\n    &copy; 2017 Michel Hua\n  </footer>\n\n  <script src=\"/dist/401cf94bec24b6efe00bb2e27c5a3d82.js\"></script>\n</body>\n</html>\n"},"hash":"06aa7ea53c65f4a85ee9e181311c0d31"}